{
    "SAS": ["AF", "BD", "BT", "IN", "MV", "NP", "PK", "LK"],
    "EEU": [
        "AL",
        "BA",
        "BG",
        "HR",
        "CZ",
        "EE",
        "HU",
        "LV",
        "LT",
        "PL",
        "RO",
        "SK",
        "SI",
        "MK"
    ],
    "MEA": [
        "DZ",
        "BH",
        "EG",
        "IR",
        "IQ",
        "IL",
        "JO",
        "KW",
        "LB",
        "LY",
        "MA",
        "OM",
        "QA",
        "SA",
        "SD",
        "SY",
        "TN",
        "AE",
        "YE"
    ],
    "PAS": [
        "AS",
        "BN",
        "FJ",
        "PF",
        "KI",
        "ID",
        "MY",
        "MM",
        "NC",
        "PG",
        "PH",
        "KR",
        "SG",
        "SB",
        "TW",
        "TH",
        "TO",
        "VU",
        "WS"
    ],
    "WEU": [
        "AD",
        "AT",
        "BE",
        "CY",
        "DK",
        "FO",
        "FI",
        "FR",
        "DE",
        "GI",
        "GR",
        "GL",
        "IS",
        "IE",
        "IM",
        "IT",
        "LI",
        "LU",
        "MT",
        "MC",
        "NL",
        "NO",
        "PT",
        "ES",
        "SE",
        "CH",
        "TR",
        "GB"
    ],
    "AFR": [
        "AO",
        "BJ",
        "BW",
        "IO",
        "BF",
        "BI",
        "CM",
        "CV",
        "CF",
        "TD",
        "KM",
        "CG",
        "CI",
        "DJ",
        "GQ",
        "ER",
        "ET",
        "GA",
        "GM",
        "GH",
        "GN",
        "GW",
        "KE",
        "LS",
        "LR",
        "MG",
        "MW",
        "ML",
        "MR",
        "MU",
        "MZ",
        "NA",
        "NE",
        "NG",
        "RE",
        "RW",
        "SH",
        "ST",
        "SN",
        "SC",
        "SL",
        "SO",
        "ZA",
        "SZ",
        "TZ",
        "TG",
        "UG",
        "ZM",
        "ZW"
    ],
    "LAM": [
        "AG",
        "AR",
        "BS",
        "BB",
        "BZ",
        "BM",
        "BO",
        "BR",
        "CL",
        "CO",
        "CR",
        "CU",
        "DM",
        "DO",
        "EC",
        "SV",
        "GF",
        "GD",
        "GP",
        "GT",
        "GY",
        "HT",
        "HN",
        "JM",
        "MQ",
        "MX",
        "NI",
        "PA",
        "PY",
        "PE",
        "KN",
        "VC",
        "LC",
        "SR",
        "TT",
        "UY",
        "VE"
    ],
    "FSU": ["AM", "AZ", "BY", "GE", "KZ", "KG", "MD", "RU", "TJ", "TM", "UA", "UZ"],
    "PAO": ["AU", "JP", "NZ"],
    "RCPA": ["KH", "KP", "LA", "MN", "VN"],
    "NAM": ["CA", "GU", "PR", "US", "VI"],
    "CHN": ["CN", "HK", "MO"]
}
